crm/__init__.py
crm/apps.py
crm/conf.py
crm/enums.py
crm/api/serializers.py
crm/api/urls.py
crm/api/views.py
crm/mgmt/commands/crm_bootstrap_demo.py
crm/models/activity.py
crm/models/config.py
crm/models/contact.py
crm/models/lead.py
crm/models/opportunity.py
crm/models/quotation.py
crm/services/converters.py
django_crm_ve-0.1.0.dist-info/licenses/LICENSE
django_crm_ve-0.1.0.dist-info/METADATA
django_crm_ve-0.1.0.dist-info/WHEEL
django_crm_ve-0.1.0.dist-info/top_level.txt
django_crm_ve-0.1.0.dist-info/RECORD
