Metadata-Version: 2.4
Name: django-crm-ve
Version: 0.1.0
Summary: Lightweight CRM for Django with leads, opportunities, quotations, and one-click conversion to sales invoices.
Author-email: "Verified Enquiries / Tushar K." <support@verifiedenquiries.com>
License: MIT
Classifier: Framework :: Django
Classifier: Programming Language :: Python :: 3
Classifier: License :: OSI Approved :: MIT License
Requires-Python: >=3.11
License-File: LICENSE
Requires-Dist: Django>=5.0
Requires-Dist: djangorestframework>=3.15
Requires-Dist: django-sales>=0.2.0
Dynamic: license-file
